<?xml version='1.0' encoding='utf8'?>
<!--
	Profile: Hannibal (7943)
	Authors: miss-aoi
-->
<!DOCTYPE Profile [
	<!-- Adjust to desired amount -->
	<!ENTITY Hannibal "1">
]>
<Profile>
	<Name>Hannibal</Name>
	<BehaviorDirectory />
	<Order>
		<Log Message="Starting Fishing: Hannibal..." />
		<If condition="not HasAtLeast(2626,50)">
			<!--Spinnerbait-->
			<Lisbeth IgnoreHome="True" Json="[{'Group':1,'Item':2626,'Amount':3,'Enabled':true,'Type':'Goldsmith'}]" />
		</If>
		<If condition="not IsOnSubMap(258)">
			<LisbethTravel Area="Northern Thanalan" XYZ="103.2273, 15.00176, 217.3866" />
		</If>
		<If condition="not ClassName == ClassJobType.Fisher">
			<ChangeClass Job="Fisher" />
		</If>
		<While condition="IsTimeBetween(21,22)">
			<WaitTimer WaitTime="30" />
		</While>
		<While condition="not HasAtLeast(7943,&Hannibal;) and HasAtLeast(2626,1) and (IsTimeBetween(22,24) or IsTimeBetween(0,4)) and ExBuddy.Helpers.SkywatcherPlugin.IsWeatherInZone(147, 'Fog')">
			<ExFish Bait="Spinnerbait" MinFish="15" MaxFish="25" ShuffleFishSpots="True" ThaliaksFavor="True" Cordial="Auto" Sit="True" Mooch="2" Patience="Patience2" MinimumGPPatience="650">
				<PatientTugs>
					<PatienceTug moochLevel="0" TugType="Light" />
					<PatienceTug moochLevel="1" TugType="Heavy" />
				</PatientTugs>
				<FishSpots>
					<FishSpot XYZ="117.044, 14.36216, 237.177" Heading="2.487101" />
					<FishSpot XYZ="118.6457, 12.16843, 221.7863" Heading="1.835743" />
					<FishSpot XYZ="132.7265, 19.5851, 207.0147" Heading="6.229785" />
				</FishSpots>
				<Keepers>
					<Keeper name="Hannibal" />
				</Keepers>
				<SurfaceSlaps />
			</ExFish>
		</While>
		<LLoadProfile Path="../../Start.xml" />
	</Order>
	<GrindAreas />
	<CodeChunks />
</Profile>