<?xml version="1.0" encoding="utf-8"?>
<!--
	Profile: Captain Nemo (17578)
	Authors: budesaal
-->
<Profile>
	<Name>Captain Nemo</Name>
	<BehaviorDirectory></BehaviorDirectory>
	<Order>

	<If condition="not HasAtLeast(17578,1)">
		<Log Message="Start Fishing: Captain Nemo..." />
		<If condition="not HasAtLeast(12711,50)">
			<Lisbeth IgnoreHome="True" Json="[{'Group':1,'Item':12711,'Amount':50,'Enabled':true,'Type':'Exchange'}]"/>
		</If>
		<If condition="not IsOnSubMap(2202)">
			<LisbethTravel ZoneId="397" XYZ="-12.63069, 90.64453, -557.0477"/>
		</If>
		<If Condition="not ClassName == ClassJobType.Fisher">
			<ChangeClass Job="Fisher" />
		</If>
		<ExFish Bait="Brute Leech" Condition="not HasAtLeast(17578,1) and ExBuddy.Helpers.SkywatcherPlugin.IsWeatherInZone(397, 'Blizzards') and ExBuddy.Helpers.SkywatcherPlugin.PredictWeatherInZone(397, TimeSpan.FromHours(-8), 'Snow')"
				MinFish="10" MaxFish="15" ShuffleFishSpots="True" SitRate=".69">
			<Keepers>
				<Keeper name="Captain Nemo" />
			</Keepers>
			<FishSpots>
				<FishSpot XYZ="-21.79417, 89.27347, -558.1567" Heading="16,570423" Sit="True"/>
			</FishSpots>
		</ExFish>
	</If>
	<LLoadProfile Path="../../Start.xml"/>
	
	</Order>
	<GrindAreas>
	</GrindAreas>
	<CodeChunks>
	</CodeChunks>
</Profile>