<?xml version='1.0' encoding='utf8'?>
<!--
	Profile: Bombardfish (7924)
	Authors: miss-aoi
-->
<!DOCTYPE Profile [
	<!-- Adjust to desired amount -->
	<!ENTITY Bombardfish "1">
]>
<Profile>
	<Name>Bombardfish</Name>
	<BehaviorDirectory />
	<Order>
		<Log Message="Starting Fishing: Bombardfish..." />
		<If condition="not HasAtLeast(2598,50)">
			<!--Herring Ball-->
			<Lisbeth IgnoreHome="True" Json="[{'Group':1,'Item':2598,'Amount':50,'Enabled':true,'Type':'Purchase'}]" />
		</If>
		<If condition="not IsOnSubMap(216)">
			<LisbethTravel Area="Eastern La Noscea" XYZ="537.0127, 8.728938, 120.3512" />
		</If>
		<If condition="not ClassName == ClassJobType.Fisher">
			<ChangeClass Job="Fisher" />
		</If>
		<While condition="Condition.IsTimeBetween(8,9)">
			<Log Message="Waiting for window to open..." />
			<WaitTimer WaitTime="30" />
		</While>
		<ExFish Bait="Herring Ball" condition="not HasAtLeast(7924,&Bombardfish;) and HasAtLeast(2598,1) and Condition.IsTimeBetween(9,15) and ExBuddy.Helpers.SkywatcherPlugin.IsWeatherInZone(137, 'Clear Skies')" MinFish="15" MaxFish="25" ShuffleFishSpots="True" ThaliaksFavor="True" CordialType="Auto" Sit="True" SitRate="1" Chum="True">
			<FishSpots>
				<FishSpot XYZ="548.963, 8.810045, 141.4665" Heading="1.354308" />
				<FishSpot XYZ="555.3425, 8.762626, 157.9973" Heading="1.748052" />
				<FishSpot XYZ="554.1113, 8.72472, 174.4444" Heading="2.003578" />
			</FishSpots>
			<Keepers>
				<Keeper name="Bombardfish" />
			</Keepers>
			<SurfaceSlaps />
		</ExFish>
		<LLoadProfile Path="../../Start.xml" />
	</Order>
	<GrindAreas />
	<CodeChunks />
</Profile>