<?xml version='1.0' encoding='utf8'?>
<!--
	Profile: Bat-o'-Nine-Tails (8766)
	Authors: miss-aoi
-->
<!DOCTYPE Profile [
	<!-- Adjust to desired amount -->
	<!ENTITY Bat-o-Nine-Tails "1">
]>
<Profile>
	<Name>Bat-o'-Nine-Tails</Name>
	<BehaviorDirectory />
	<Order>
		<Log Message="Starting Fishing: Bat-o-Nine-Tails..." />
		<If condition="not HasAtLeast(2599,50)">
			<!--Honey Worm-->
			<Lisbeth IgnoreHome="True" Json="[{'Group':1,'Item':2599,'Amount':50,'Enabled':true,'Type':'Purchase'}]" />
		</If>
		<If condition="not IsOnSubMap(276)">
			<LisbethTravel Area="Western Thanalan" XYZ="-345.541, 14.71903, -739.8731" />
		</If>
		<If condition="not ClassName == ClassJobType.Fisher">
			<ChangeClass Job="Fisher" />
		</If>
		<While condition="not HasAtLeast(8766,&Bat-o-Nine-Tails;) and HasAtLeast(2599,1) and ExBuddy.Helpers.SkywatcherPlugin.IsWeatherInZone(140, 'Clear Skies', 'Clouds', 'Fog', 'Fair Skies') and ExBuddy.Helpers.SkywatcherPlugin.PredictWeatherInZone(140, TimeSpan.FromHours(-8), 'Clear Skies', 'Clouds', 'Fog', 'Fair Skies')">
			<ExFish Bait="Honey Worm" MinFish="15" MaxFish="25" ShuffleFishSpots="True" ThaliaksFavor="True" Cordial="Auto" Sit="True" Mooch="2" Patience="Patience2" MinimumGPPatience="650">
				<PatientTugs>
					<PatienceTug moochLevel="0" TugType="Light" />
					<PatienceTug moochLevel="1" TugType="Heavy" />
				</PatientTugs>
				<FishSpots>
					<FishSpot XYZ="-317.0771, 12.60398, -741.5321" Heading="0.7704749" />
					<FishSpot XYZ="-323.1062, 12.59304, -717.5994" Heading="3.243963" />
					<FishSpot XYZ="-336.2919, 12.74882, -741.1483" Heading="1.777886" />
				</FishSpots>
				<Keepers>
					<Keeper name="Bat-o'-Nine-Tails" />
				</Keepers>
				<SurfaceSlaps />
			</ExFish>
		</While>
		<LLoadProfile Path="../../Start.xml" />
	</Order>
	<GrindAreas />
	<CodeChunks />
</Profile>